{"words":[{"w":"When","s":14.66,"e":15.5,"line":0},{"w":"the","s":15.5,"e":16.34,"line":0},{"w":"world","s":16.34,"e":16.7,"line":0},{"w":"gets","s":16.7,"e":17.14,"line":0},{"w":"heavy,","s":17.14,"e":17.52,"line":0},{"w":"I","s":18,"e":18.02,"line":0},{"w":"wanna","s":18.02,"e":18.24,"line":0},{"w":"climb","s":18.76,"e":18.76,"line":0},{"w":"high","s":18.76,"e":19.6,"line":0},{"w":"Swing","s":19.6,"e":20.1,"line":1},{"w":"on","s":20.1,"e":20.4,"line":1},{"w":"a","s":20.4,"e":20.82,"line":1},{"w":"birch","s":20.82,"e":20.94,"line":1},{"w":"tree,","s":20.94,"e":21.26,"line":1},{"w":"touch","s":21.7,"e":21.74,"line":1},{"w":"the","s":21.74,"e":22.54,"line":1},{"w":"sky","s":22.54,"e":22.54,"line":1},{"w":"Leave","s":22.54,"e":23.48,"line":2},{"w":"for","s":23.48,"e":23.92,"line":2},{"w":"a","s":23.92,"e":24.3,"line":2},{"w":"minute,","s":24.3,"e":24.3,"line":2},{"w":"but","s":24.34,"e":24.64,"line":2},{"w":"I","s":24.64,"e":24.92,"line":2},{"w":"won’t","s":24.92,"e":25.01,"line":2},{"w":"stay","s":25.1,"e":25.64,"line":2},{"w":"gone","s":25.64,"e":26.16,"line":2},{"w":"Come","s":26.16,"e":26.56,"line":3},{"w":"back","s":26.56,"e":27.14,"line":3},{"w":"to","s":27.14,"e":27.38,"line":3},{"w":"earth","s":27.38,"e":27.76,"line":3},{"w":"and","s":27.76,"e":28.06,"line":3},{"w":"keep","s":28.06,"e":28.44,"line":3},{"w":"moving","s":28.44,"e":29.16,"line":3},{"w":"on","s":29.16,"e":30.48,"line":3},{"w":"Frost","s":42.74,"e":43.5,"line":4},{"w":"saw","s":43.5,"e":44,"line":4},{"w":"bent","s":44,"e":44.38,"line":4},{"w":"trees","s":44.38,"e":44.88,"line":4},{"w":"and","s":44.88,"e":45.26,"line":4},{"w":"thought","s":45.26,"e":45.5,"line":4},{"w":"of","s":45.5,"e":45.76,"line":4},{"w":"a","s":45.76,"e":46.1,"line":4},{"w":"boy","s":46.1,"e":46.36,"line":4},{"w":"Climbing","s":46.36,"e":47.24,"line":5},{"w":"for","s":47.24,"e":47.58,"line":5},{"w":"freedom,","s":47.58,"e":48.16,"line":5},{"w":"climbing","s":48.9,"e":48.94,"line":5},{"w":"for","s":48.94,"e":49.64,"line":5},{"w":"joy","s":49.64,"e":49.64,"line":5},{"w":"But","s":49.64,"e":50.3,"line":6},{"w":"life","s":50.3,"e":50.8,"line":6},{"w":"bends","s":50.8,"e":51.06,"line":6},{"w":"people","s":51.06,"e":51.56,"line":6},{"w":"like","s":51.56,"e":52.04,"line":6},{"w":"ice","s":52.04,"e":52.44,"line":6},{"w":"bends","s":52.44,"e":52.76,"line":6},{"w":"trees","s":52.76,"e":53.36,"line":6},{"w":"Still","s":53.36,"e":53.88,"line":7},{"w":"we","s":53.88,"e":54.2,"line":7},{"w":"dream","s":54.2,"e":54.58,"line":7},{"w":"upward","s":54.58,"e":54.98,"line":7},{"w":"when","s":54.98,"e":55.18,"line":7},{"w":"we","s":55.18,"e":55.48,"line":7},{"w":"need","s":55.48,"e":55.82,"line":7},{"w":"release","s":55.82,"e":56.14,"line":7},{"w":"Not","s":56.14,"e":57,"line":8},{"w":"running","s":57,"e":57.5,"line":8},{"w":"forever","s":57.5,"e":58.6,"line":8},{"w":"Just","s":58.6,"e":60.44,"line":9},{"w":"breathing","s":60.44,"e":60.86,"line":9},{"w":"a","s":60.86,"e":62,"line":9},{"w":"while","s":62,"e":62,"line":9},{"w":"A","s":62,"e":63.44,"line":10},{"w":"small","s":63.44,"e":64.06,"line":10},{"w":"trip","s":64.06,"e":64.36,"line":10},{"w":"to","s":64.36,"e":65.42,"line":10},{"w":"heaven","s":65.42,"e":65.42,"line":10},{"w":"Then","s":66.66,"e":67.2,"line":11},{"w":"back","s":67.2,"e":67.5,"line":11},{"w":"with","s":67.5,"e":67.8,"line":11},{"w":"a","s":67.8,"e":67.98,"line":11},{"w":"smile","s":67.98,"e":70.1,"line":11},{"w":"When","s":70.1,"e":70.44,"line":12},{"w":"the","s":70.44,"e":70.92,"line":12},{"w":"world","s":70.92,"e":71.06,"line":12},{"w":"gets","s":71.06,"e":71.52,"line":12},{"w":"heavy,","s":71.52,"e":71.94,"line":12},{"w":"I","s":71.94,"e":72.36,"line":12},{"w":"wanna","s":72.36,"e":72.54,"line":12},{"w":"climb","s":72.72,"e":73.14,"line":12},{"w":"high","s":73.14,"e":73.78,"line":12},{"w":"Swing","s":73.78,"e":74.46,"line":13},{"w":"on","s":74.46,"e":74.78,"line":13},{"w":"a","s":74.78,"e":75.18,"line":13},{"w":"birch","s":75.18,"e":75.3,"line":13},{"w":"tree,","s":75.3,"e":75.6,"line":13},{"w":"touch","s":76.04,"e":76.06,"line":13},{"w":"the","s":76.06,"e":76.92,"line":13},{"w":"sky","s":76.92,"e":76.92,"line":13},{"w":"Leave","s":76.96,"e":77.82,"line":14},{"w":"for","s":77.82,"e":78.16,"line":14},{"w":"a","s":78.16,"e":78.64,"line":14},{"w":"minute,","s":78.64,"e":78.64,"line":14},{"w":"but","s":78.64,"e":78.96,"line":14},{"w":"I","s":78.96,"e":79.32,"line":14},{"w":"won’t","s":79.32,"e":79.37,"line":14},{"w":"stay","s":79.42,"e":79.98,"line":14},{"w":"gone","s":79.98,"e":80.38,"line":14},{"w":"Come","s":100.82,"e":101.54,"line":15},{"w":"back","s":101.54,"e":102.26,"line":15},{"w":"to","s":102.26,"e":102.28,"line":15},{"w":"earth","s":102.28,"e":102.38,"line":15},{"w":"and","s":102.38,"e":102.82,"line":15},{"w":"keep","s":102.82,"e":102.82,"line":15},{"w":"moving","s":102.82,"e":102.82,"line":15},{"w":"on","s":102.82,"e":102.82,"line":15}],"lines":[{"s":14.66,"e":19.6,"text":"When the world gets heavy, I wanna climb high"},{"s":19.6,"e":22.54,"text":"Swing on a birch tree, touch the sky"},{"s":22.54,"e":26.16,"text":"Leave for a minute, but I won’t stay gone"},{"s":26.16,"e":30.48,"text":"Come back to earth and keep moving on"},{"s":42.74,"e":46.36,"text":"Frost saw bent trees and thought of a boy"},{"s":46.36,"e":49.64,"text":"Climbing for freedom, climbing for joy"},{"s":49.64,"e":53.36,"text":"But life bends people like ice bends trees"},{"s":53.36,"e":56.14,"text":"Still we dream upward when we need release"},{"s":56.14,"e":58.6,"text":"Not running forever"},{"s":58.6,"e":62,"text":"Just breathing a while"},{"s":62,"e":65.42,"text":"A small trip to heaven"},{"s":66.66,"e":70.1,"text":"Then back with a smile"},{"s":70.1,"e":73.78,"text":"When the world gets heavy, I wanna climb high"},{"s":73.78,"e":76.92,"text":"Swing on a birch tree, touch the sky"},{"s":76.96,"e":80.38,"text":"Leave for a minute, but I won’t stay gone"},{"s":100.82,"e":102.82,"text":"Come back to earth and keep moving on"}],"duration":102.84,"source":"whisper-aligned","generatedAt":"2026-05-25T06:38:40.284Z","stats":{"whisperWords":128,"polishedWords":120,"matched":118,"matchRate":0.983}}